hexagen/__init__.py
hexagen-1.2.data/scripts/hexagen
hexagen-1.2.dist-info/LICENSE
hexagen-1.2.dist-info/METADATA
hexagen-1.2.dist-info/WHEEL
hexagen-1.2.dist-info/top_level.txt
hexagen-1.2.dist-info/RECORD
