Metadata-Version: 2.1
Name: hexagen
Version: 1.2
Summary: Generates random hexadecimal digits and prints them to standard output.
Home-page: https://github.com/cabrust/hexagen
Author: Clemens-Alexander Brust
Author-email: ikosa.de@gmail.com
License: UNKNOWN
Platform: UNKNOWN
Classifier: Programming Language :: Python :: 3
Classifier: Operating System :: OS Independent
Classifier: License :: OSI Approved :: BSD License
Requires-Python: >=3.6
